pyduin/__init__.py
pyduin/arduino.py
pyduin/arduino_cli.py
pyduin/pin.py
pyduin/utils.py
pyduin/data/boardfiles/nanoatmega328.yml
pyduin/data/boardfiles/sparkfun_promicro16.yml
pyduin/data/boardfiles/uno.yml
pyduin/data/platformio/platformio.ini
pyduin-0.6.4.dist-info/LICENSE.md
pyduin-0.6.4.dist-info/METADATA
pyduin-0.6.4.dist-info/WHEEL
pyduin-0.6.4.dist-info/entry_points.txt
pyduin-0.6.4.dist-info/top_level.txt
pyduin-0.6.4.dist-info/RECORD
