Metadata-Version: 2.1
Name: pyduin
Version: 0.6.4
Summary: Extensive Arduino abstraction
Author-email: Steffen Kockel <info@steffen-kockel.de>
License: GPLv3
Project-URL: Homepage, http://github.com/SteffenKockel/pyduin
Project-URL: Documentation, http://github.com/SteffenKockel/pyduin
Project-URL: Source, http://github.com/SteffenKockel/pyduin
Project-URL: Tracker, http://github.com/SteffenKockel/pyduin/issues
Classifier: Development Status :: 4 - Beta
Classifier: Intended Audience :: Developers
Classifier: License :: OSI Approved :: GNU General Public License v3 (GPLv3)
Classifier: Programming Language :: Python :: 3
Classifier: Topic :: Software Development :: Libraries :: Python Modules
Requires-Python: >3
License-File: LICENSE.md
Requires-Dist: cpplint
Requires-Dist: jinja2
Requires-Dist: platformio
Requires-Dist: PyYAML
Requires-Dist: pyserial
Requires-Dist: requests
Requires-Dist: termcolor
